odoo/addons/website_signup_additional_fields/README.rst
odoo/addons/website_signup_additional_fields/__init__.py
odoo/addons/website_signup_additional_fields/__manifest__.py
odoo/addons/website_signup_additional_fields/i18n/es.po
odoo/addons/website_signup_additional_fields/models/__init__.py
odoo/addons/website_signup_additional_fields/models/res_config_settings.py
odoo/addons/website_signup_additional_fields/models/res_users.py
odoo/addons/website_signup_additional_fields/models/website.py
odoo/addons/website_signup_additional_fields/static/description/icon.png
odoo/addons/website_signup_additional_fields/views/res_config_settings_views.xml
odoo_addon_website_signup_additional_fields-15.0.1.0.0.4.dist-info/METADATA
odoo_addon_website_signup_additional_fields-15.0.1.0.0.4.dist-info/WHEEL
odoo_addon_website_signup_additional_fields-15.0.1.0.0.4.dist-info/top_level.txt
odoo_addon_website_signup_additional_fields-15.0.1.0.0.4.dist-info/RECORD
